[{"id":17488,"name":"Thot","uri":"\/artists\/17488-thot?utm_source=4951&utm_medium=partner"},{"id":162811,"name":"Zuul Fx","uri":"\/artists\/162811-zuul-fx?utm_source=4951&utm_medium=partner"},{"id":514950,"name":"Loudblast","uri":"\/artists\/514950-loudblast?utm_source=4951&utm_medium=partner"},{"id":513614,"name":"L'Esprit du Clan","uri":"\/artists\/513614-lesprit-du-clan?utm_source=4951&utm_medium=partner"},{"id":4251436,"name":"Rise of the Northstar","uri":"\/artists\/4251436-rise-of-the-northstar?utm_source=4951&utm_medium=partner"},{"id":1626606,"name":"KOmaH","uri":"\/artists\/1626606-komah?utm_source=4951&utm_medium=partner"},{"id":4624418,"name":"When Diamonds Fade","uri":"\/artists\/4624418-when-diamonds-fade?utm_source=4951&utm_medium=partner"}]