[{"id":894745,"name":"Meursault","uri":"\/artists\/894745-meursault?utm_source=4951&utm_medium=partner"},{"id":589752,"name":"Found","uri":"\/artists\/589752-found?utm_source=4951&utm_medium=partner"},{"id":1987431,"name":"Endor","uri":"\/artists\/1987431-endor?utm_source=4951&utm_medium=partner"},{"id":2324838,"name":"French Wives","uri":"\/artists\/2324838-french-wives?utm_source=4951&utm_medium=partner"},{"id":79612,"name":"Letters","uri":"\/artists\/79612-letters?utm_source=4951&utm_medium=partner"},{"id":1029163,"name":"esperi","uri":"\/artists\/1029163-esperi?utm_source=4951&utm_medium=partner"},{"id":1886735,"name":"Yahweh","uri":"\/artists\/1886735-yahweh?utm_source=4951&utm_medium=partner"},{"id":2343020,"name":"Dead Boy Robotics","uri":"\/artists\/2343020-dead-boy-robotics?utm_source=4951&utm_medium=partner"},{"id":920778,"name":"Paws","uri":"\/artists\/920778-paws?utm_source=4951&utm_medium=partner"},{"id":2398766,"name":"Trapped in Kansas","uri":"\/artists\/2398766-trapped-in-kansas?utm_source=4951&utm_medium=partner"},{"id":2361274,"name":"Sebastian Dangerfield","uri":"\/artists\/2361274-sebastian-dangerfield?utm_source=4951&utm_medium=partner"},{"id":3596161,"name":"Verse Metrics","uri":"\/artists\/3596161-verse-metrics?utm_source=4951&utm_medium=partner"},{"id":4112021,"name":"The Spook School","uri":"\/artists\/4112021-spook-school?utm_source=4951&utm_medium=partner"}]