[{"id":2386218,"name":"Auction for the Promise Club","uri":"\/artists\/2386218-auction-for-the-promise-club?utm_source=4951&utm_medium=partner"},{"id":2466006,"name":"Willie & the Bandits","uri":"\/artists\/2466006-willie-and-the-bandits?utm_source=4951&utm_medium=partner"},{"id":3456941,"name":"Rosie Vanier","uri":"\/artists\/3456941-rosie-vanier?utm_source=4951&utm_medium=partner"},{"id":4053541,"name":"Hedluv and Passman","uri":"\/artists\/4053541-hedluv-and-passman?utm_source=4951&utm_medium=partner"}]