[{"id":97954,"name":"Guus Meeuwis","uri":"\/artists\/97954-guus-meeuwis?utm_source=4951&utm_medium=partner"},{"id":290562,"name":"Don Diablo","uri":"\/artists\/290562-don-diablo?utm_source=4951&utm_medium=partner"},{"id":457544,"name":"The Opposites","uri":"\/artists\/457544-opposites?utm_source=4951&utm_medium=partner"},{"id":255424,"name":"Erick E","uri":"\/artists\/255424-erick-e?utm_source=4951&utm_medium=partner"},{"id":2449651,"name":"Miss Montreal","uri":"\/artists\/2449651-miss-montreal?utm_source=4951&utm_medium=partner"},{"id":932040,"name":"Destine","uri":"\/artists\/932040-destine?utm_source=4951&utm_medium=partner"},{"id":563150,"name":"Peter Pan Speedrock","uri":"\/artists\/563150-peter-pan-speedrock?utm_source=4951&utm_medium=partner"},{"id":62056,"name":"Handsome Poets","uri":"\/artists\/62056-handsome-poets?utm_source=4951&utm_medium=partner"},{"id":338957,"name":"Baskerville","uri":"\/artists\/338957-baskerville?utm_source=4951&utm_medium=partner"},{"id":377450,"name":"Heideroosjes","uri":"\/artists\/377450-heideroosjes?utm_source=4951&utm_medium=partner"},{"id":868895,"name":"Nobody Beats the Drum","uri":"\/artists\/868895-nobody-beats-the-drum?utm_source=4951&utm_medium=partner"},{"id":30487,"name":"Paul Elstak","uri":"\/artists\/30487-paul-elstak?utm_source=4951&utm_medium=partner"},{"id":517214,"name":"The Deaf","uri":"\/artists\/517214-deaf?utm_source=4951&utm_medium=partner"},{"id":1373995,"name":"Boef en de Gelogeerde Aap","uri":"\/artists\/1373995-boef-en-de-gelogeerde-aap?utm_source=4951&utm_medium=partner"},{"id":66335,"name":"Band Zonder Banaan","uri":"\/artists\/66335-band-zonder-banaan?utm_source=4951&utm_medium=partner"},{"id":2606686,"name":"Memphis Maniacs","uri":"\/artists\/2606686-memphis-maniacs?utm_source=4951&utm_medium=partner"},{"id":1664797,"name":"Cursed P","uri":"\/artists\/1664797-cursed-p?utm_source=4951&utm_medium=partner"}]