[{"id":3611766,"name":"Aphrodite","uri":"\/artists\/3611766-aphrodite?utm_source=4951&utm_medium=partner"},{"id":413811,"name":"Marcel et son Orchestre","uri":"\/artists\/413811-marcel-et-son-orchestre?utm_source=4951&utm_medium=partner"},{"id":1079321,"name":"Tim and Puma Mimi","uri":"\/artists\/1079321-tim-and-puma-mimi?utm_source=4951&utm_medium=partner"},{"id":1029600,"name":"Mark Kelly","uri":"\/artists\/1029600-mark-kelly?utm_source=4951&utm_medium=partner"},{"id":451055,"name":"Valiumvalse","uri":"\/artists\/451055-valiumvalse?utm_source=4951&utm_medium=partner"},{"id":201817,"name":"Toufo","uri":"\/artists\/201817-toufo?utm_source=4951&utm_medium=partner"},{"id":4676628,"name":"Passion Du Sud","uri":"\/artists\/4676628-passion-du-sud?utm_source=4951&utm_medium=partner"}]