[{"id":838326,"name":"Young Boys","uri":"\/artists\/838326-young-boys?utm_source=4951&utm_medium=partner"},{"id":4340151,"name":"You Won't","uri":"\/artists\/4340151-you-wont?utm_source=4951&utm_medium=partner"},{"id":281713,"name":"Adam's Castle","uri":"\/artists\/281713-adams-castle?utm_source=4951&utm_medium=partner"},{"id":3403406,"name":"La Defense","uri":"\/artists\/3403406-la-defense?utm_source=4951&utm_medium=partner"},{"id":697107,"name":"Paper Fleet","uri":"\/artists\/697107-paper-fleet?utm_source=4951&utm_medium=partner"},{"id":3179891,"name":"The Long Eye","uri":"\/artists\/3179891-long-eye?utm_source=4951&utm_medium=partner"}]