[{"id":274751,"name":"Tulus","uri":"\/artists\/274751-tulus?utm_source=4951&utm_medium=partner"},{"id":3070646,"name":"Prietto Viaja Al Cosmos Con Mariano","uri":"\/artists\/3070646-prietto-viaja-al-cosmos-con-mariano?utm_source=4951&utm_medium=partner"},{"id":1075968,"name":"Holy Piby","uri":"\/artists\/1075968-holy-piby?utm_source=4951&utm_medium=partner"},{"id":4488238,"name":"Morbo & Mambo","uri":"\/artists\/4488238-morbo-and-mambo?utm_source=4951&utm_medium=partner"},{"id":4692028,"name":"Los Cocineros","uri":"\/artists\/4692028-los-cocineros?utm_source=4951&utm_medium=partner"},{"id":4692023,"name":"Inclan","uri":"\/artists\/4692023-inclan?utm_source=4951&utm_medium=partner"},{"id":2655261,"name":"Proyecto Gomez","uri":"\/artists\/2655261-proyecto-gomez?utm_source=4951&utm_medium=partner"},{"id":4692038,"name":"Lo Pibitos","uri":"\/artists\/4692038-lo-pibitos?utm_source=4951&utm_medium=partner"},{"id":4692018,"name":"Paula Maffia Y La Cosa Mostra","uri":"\/artists\/4692018-paula-maffia-y-la-cosa-mostra?utm_source=4951&utm_medium=partner"}]