[{"id":517568,"name":"Montana","uri":"\/artists\/517568-montana?utm_source=4951&utm_medium=partner"},{"id":4709903,"name":"Boogie Boy Guescio","uri":"\/artists\/4709903-boogie-boy-guescio?utm_source=4951&utm_medium=partner"},{"id":4709923,"name":"Jolly Jolly Doowhacker","uri":"\/artists\/4709923-jolly-jolly-doowhacker?utm_source=4951&utm_medium=partner"},{"id":4709908,"name":"The Bang Up","uri":"\/artists\/4709908-bang-up?utm_source=4951&utm_medium=partner"},{"id":4709928,"name":"Gli Ebrei","uri":"\/artists\/4709928-gli-ebrei?utm_source=4951&utm_medium=partner"}]