[{"id":525609,"name":"Agalloch","uri":"\/artists\/525609-agalloch?utm_source=4951&utm_medium=partner"},{"id":4980,"name":"Borknagar","uri":"\/artists\/4980-borknagar?utm_source=4951&utm_medium=partner"},{"id":134161,"name":"Absu","uri":"\/artists\/134161-absu?utm_source=4951&utm_medium=partner"},{"id":353936,"name":"Skyclad","uri":"\/artists\/353936-skyclad?utm_source=4951&utm_medium=partner"},{"id":114374,"name":"Wolfchant","uri":"\/artists\/114374-wolfchant?utm_source=4951&utm_medium=partner"},{"id":2613631,"name":"A Forest of Stars","uri":"\/artists\/2613631-a-forest-of-stars?utm_source=4951&utm_medium=partner"},{"id":27000,"name":"Mael Mordha","uri":"\/artists\/27000-mael-mordha?utm_source=4951&utm_medium=partner"},{"id":208497,"name":"Rabenschrey","uri":"\/artists\/208497-rabenschrey?utm_source=4951&utm_medium=partner"},{"id":469014,"name":"Fejd","uri":"\/artists\/469014-fejd?utm_source=4951&utm_medium=partner"},{"id":3640506,"name":"Dordeduh","uri":"\/artists\/3640506-dordeduh?utm_source=4951&utm_medium=partner"},{"id":887815,"name":"Voluspaa","uri":"\/artists\/887815-voluspaa?utm_source=4951&utm_medium=partner"},{"id":4808908,"name":"King of Asgard","uri":"\/artists\/4808908-king-of-asgard?utm_source=4951&utm_medium=partner"}]